Metadata-Version: 2.1
Name: odoo14-addon-product-barcode-constraint-per-company
Version: 14.0.1.1.1.dev4
Summary: Change the product barcode constraint, allowing the same barcode for differents companies
Home-page: https://github.com/OCA/stock-logistics-barcode
Author: GRAP, Odoo Community Association (OCA)
Author-email: support@odoo-community.org
License: AGPL-3
Platform: UNKNOWN
Classifier: Programming Language :: Python
Classifier: Framework :: Odoo
Classifier: Framework :: Odoo :: 14.0
Classifier: License :: OSI Approved :: GNU Affero General Public License v3
Requires-Python: >=3.6
Requires-Dist: odoo14-addon-product-variant-company
Requires-Dist: odoo <14.1dev,>=14.0a
